topsis_yuvraj_102303119/__init__.py
topsis_yuvraj_102303119/topsis.py
topsis_yuvraj_102303119-1.0.4.dist-info/METADATA
topsis_yuvraj_102303119-1.0.4.dist-info/WHEEL
topsis_yuvraj_102303119-1.0.4.dist-info/entry_points.txt
topsis_yuvraj_102303119-1.0.4.dist-info/top_level.txt
topsis_yuvraj_102303119-1.0.4.dist-info/RECORD
