Metadata-Version: 2.4
Name: topsis-yuvraj-102303119
Version: 1.0.4
Requires-Dist: numpy
Requires-Dist: pandas
Dynamic: requires-dist
